rancher.py
rancher_client_python_3p-0.2.0.dist-info/LICENSE.txt
rancher_client_python_3p-0.2.0.dist-info/METADATA
rancher_client_python_3p-0.2.0.dist-info/WHEEL
rancher_client_python_3p-0.2.0.dist-info/top_level.txt
rancher_client_python_3p-0.2.0.dist-info/RECORD
