Metadata-Version: 2.1
Name: rancher-client-python-3p
Version: 0.2.0
Summary: Python client for the Rancher API
Home-page: https://github.com/rancher/client-python
License: MIT Style
Platform: UNKNOWN
Classifier: Intended Audience :: Developers
Classifier: License :: OSI Approved :: MIT License
Classifier: Programming Language :: Python :: 3.7
Classifier: Topic :: Software Development :: Libraries
Requires-Dist: requests
